sse_starlette/__init__.py
sse_starlette/event.py
sse_starlette/py.typed
sse_starlette/sse.py
sse_starlette-3.0.1.dist-info/licenses/AUTHORS
sse_starlette-3.0.1.dist-info/licenses/LICENSE
sse_starlette-3.0.1.dist-info/METADATA
sse_starlette-3.0.1.dist-info/WHEEL
sse_starlette-3.0.1.dist-info/top_level.txt
sse_starlette-3.0.1.dist-info/RECORD
